flask_bigapp_edge/__init__.py
flask_bigapp_edge/auth.py
flask_bigapp_edge/bigapp.py
flask_bigapp_edge/blueprint.py
flask_bigapp_edge/resources.py
flask_bigapp_edge/security.py
flask_bigapp_edge/utilities.py
flask_bigapp_edge_cli/__init__.py
flask_bigapp_edge_cli/cli.py
flask_bigapp_edge_cli/resources.py
Flask_BigApp_Edge-0.2.dist-info/LICENSE
Flask_BigApp_Edge-0.2.dist-info/METADATA
Flask_BigApp_Edge-0.2.dist-info/WHEEL
Flask_BigApp_Edge-0.2.dist-info/entry_points.txt
Flask_BigApp_Edge-0.2.dist-info/top_level.txt
Flask_BigApp_Edge-0.2.dist-info/RECORD
