Metadata-Version: 2.1
Name: Flask-BigApp-Edge
Version: 0.2
Summary: This is the edge build of Flask-BigApp, this built may be very unstable, or not work at all. Version numbers will change a lot!
Home-page: https://github.com/CheeseCake87/Flask-BigApp/tree/edge
Author: David Carmichael
Author-email: carmichaelits@gmail.com
License: GNU General Public License v2 or later (GPLv2+)
Platform: any
Classifier: Environment :: Web Environment
Classifier: Intended Audience :: Developers
Classifier: License :: OSI Approved :: GNU General Public License v2 or later (GPLv2+)
Classifier: Operating System :: OS Independent
Classifier: Programming Language :: Python
Classifier: Programming Language :: Python :: 3.8
Classifier: Topic :: Internet :: WWW/HTTP :: Dynamic Content
Classifier: Topic :: Software Development :: Libraries :: Python Modules
Classifier: Natural Language :: English
License-File: LICENSE
Requires-Dist: Flask
Requires-Dist: Flask-SQLAlchemy
Requires-Dist: toml
Provides-Extra: testing
Requires-Dist: pytest (>=6.0) ; extra == 'testing'
Requires-Dist: pytest-cov (>=2.0) ; extra == 'testing'
Requires-Dist: mypy (>=0.910) ; extra == 'testing'
Requires-Dist: flake8 (>=3.9) ; extra == 'testing'
Requires-Dist: tox (>=3.24) ; extra == 'testing'
